Metadata-Version: 2.1
Name: KEGGRESTpy
Version: 0.1.2
Summary: A Python wrapper for accessing KEGG REST API, inspired by KEGGREST in Bioconductor
Home-page: https://github.com/guokai8/KEGGRESTpy
Author: Kai Guo
Author-email: guokai8@gmail.com
Classifier: Programming Language :: Python :: 3
Classifier: License :: OSI Approved :: MIT License
Classifier: Operating System :: OS Independent
Requires-Python: >=3.6
License-File: LICENSE
